.bumpversion.cfg
.coveragerc
.editorconfig
AUTHORS.rst
CHANGELOG.rst
CONTRIBUTING.rst
LICENSE
MANIFEST.in
README.rst
setup.cfg
setup.py
tox.ini
ci/bootstrap.py
src/drupal_hash_utility/__init__.py
src/drupal_hash_utility/__main__.py
src/drupal_hash_utility/cli.py
src/drupal_hash_utility.egg-info/PKG-INFO
src/drupal_hash_utility.egg-info/SOURCES.txt
src/drupal_hash_utility.egg-info/dependency_links.txt
src/drupal_hash_utility.egg-info/entry_points.txt
src/drupal_hash_utility.egg-info/not-zip-safe
src/drupal_hash_utility.egg-info/top_level.txt
tests/test_drupal_hash_utility.py