Metadata-Version: 1.2
Name: drupal-hash-utility
Version: 0.3.6
Summary: A hashing utility built from Drupal7 specification.
Home-page: https://gitlab.com/thaxoo/drupal_hash_utility
Author: Elliott Neal
Author-email: elliott.neal@ghostlyhaks.com
License: MIT license
Project-URL: Changelog, https://gitlab.com/thaxoo/drupal_hash_utility/blob/master/CHANGELOG.rst
Project-URL: Issue Tracker, https://gitlab.com/thaxoo/drupal_hash_utility/issues
Keywords: drupal,hash,password
Platform: UNKNOWN
Classifier: Development Status :: 5 - Production/Stable
Classifier: Intended Audience :: Developers
Classifier: License :: OSI Approved :: MIT License
Classifier: Operating System :: Unix
Classifier: Operating System :: POSIX
Classifier: Operating System :: Microsoft :: Windows
Classifier: Programming Language :: Python
Classifier: Programming Language :: Python :: 3
Classifier: Programming Language :: Python :: 3.6
Classifier: Programming Language :: Python :: 3.7
Classifier: Programming Language :: Python :: Implementation :: CPython
Classifier: Programming Language :: Python :: Implementation :: PyPy
Classifier: Topic :: Utilities
Requires-Python: >=3.6
